xchk_multiple_choice_strategies/MultipleChoiceChecker.py
xchk_multiple_choice_strategies/MultipleChoiceLexer.py
xchk_multiple_choice_strategies/MultipleChoiceListener.py
xchk_multiple_choice_strategies/MultipleChoiceParser.py
xchk_multiple_choice_strategies/MultipleChoicePrinter.py
xchk_multiple_choice_strategies/__init__.py
xchk_multiple_choice_strategies/apps.py
xchk_multiple_choice_strategies/strats.py
xchk_multiple_choice_strategies/tests.py
xchk_multiple_choice_strategies-0.0.2.dist-info/WHEEL
xchk_multiple_choice_strategies-0.0.2.dist-info/METADATA
xchk_multiple_choice_strategies-0.0.2.dist-info/RECORD
