Metadata-Version: 2.1
Name: xchk-multiple-choice-strategies
Version: 0.0.2
Summary: Checks and strategies for multiple choice questions in the xchk system
License: MIT
Author: Vincent Nys
Author-email: vincentnys@gmail.com
Requires-Python: >=3.7,<4.0
Classifier: License :: OSI Approved :: MIT License
Classifier: Programming Language :: Python :: 3
Classifier: Programming Language :: Python :: 3.7
Classifier: Programming Language :: Python :: 3.8
Classifier: Programming Language :: Python :: 3.9
Requires-Dist: antlr4-python3-runtime (>=4.8,<5.0)
